{
  "project_number": 3,
  "post_url": "https://www.facebook.com/garynixonrooofing/posts/pfbid015AXVbx5D15w1B6LijkaRWYbKmKNpERJid7zoZpyV5w78mRAuaoUd28kUBsdmVhkl",
  "text": "New roof recently just completed 😀\n\nNew roof, faicas, sofits, gutters and down pipes all supplied and fitted happy customers great effort from my work team once again 👌😁\n\nWe are a family run local roofing company who provide services to Kilmarnock, Ayrshire and surrounding areas. 💧🏠\n\nWe are fully insured, qualified tradesman and use British Standard approved materials. All new roofs come with a 10 year guarantee. ✅\n\nNo payment required until customer is fully satisfied. ✅\n\nALL NEW ROOFS SCAFFOLDING FREE OF CHARGE 🔥🔥🔥🔥\n\n◾Re-Roofing \n◾️Roof Maintenance \n◾️Roof Repairs\n◾️Emergency Roof Repairs\n◾️Flat Roofing \n◾️corrugated sheeting roofs \n◾️ Roof cleaning & biocide treatment \n◾️Lead work \n◾️Facias & soffits\n◾️ Gutter cleaning + new gutters \n◾️Scaffolding \n\n◾Free quotes & Fully Insured \nI\nEmail📧 gnroofingscaffoldingservices@gmail.com\n\nPhone📲￼⁨07710 981903⁩",
  "likes": 11,
  "comments": 1,
  "shares": 41,
  "images": [
    {
      "filename": "image_001.jpg",
      "url": "https://scontent-iad3-1.xx.fbcdn.net/v/t39.30808-6/486162270_1059008906244815_6854270113338535226_n.jpg?stp=cp6_dst-jpg_s590x590_tt6&_nc_cat=107&ccb=1-7&_nc_sid=833d8c&_nc_ohc=Q66lnFOjZ18Q7kNvwH_50tI&_nc_oc=AdkbGXjaitPt2JDhzFX2jokmq-hUbauYaLbOEjCGMIovamwp6r3_AIlfQokw8shaP6c&_nc_zt=23&_nc_ht=scontent-iad3-1.xx&_nc_gid=N0x--LuBn_wwHALEPHtXKw&oh=00_Afgwh4vAgi0h29njcAkBt3wsmF_3EtB1zhJrVeX44_ym7g&oe=6927B553",
      "width": 443,
      "height": 590,
      "id": "1021687113310328"
    },
    {
      "filename": "image_002.jpg",
      "url": "https://scontent-iad3-1.xx.fbcdn.net/v/t39.30808-6/486381005_1059009159578123_3558540019455453704_n.jpg?stp=cp6_dst-jpg_s590x590_tt6&_nc_cat=107&ccb=1-7&_nc_sid=833d8c&_nc_ohc=TarO9hAWb-wQ7kNvwFG7But&_nc_oc=AdlkC8gdCqZ367urW7-TV364H90Z5ldzYXAyQXLAvn6utStYxCDQhr04b8ovNN4Y2Uk&_nc_zt=23&_nc_ht=scontent-iad3-1.xx&_nc_gid=N0x--LuBn_wwHALEPHtXKw&oh=00_AfjT_UuXYqOzg3d8_h_gDlBz4toAXyPJMph5bxkGHK0OXw&oe=6927B6C9",
      "width": 443,
      "height": 590,
      "id": "1021687273310312"
    },
    {
      "filename": "image_003.jpg",
      "url": "https://scontent-iad3-2.xx.fbcdn.net/v/t39.30808-6/486161644_1059009206244785_8883042970868265954_n.jpg?stp=cp6_dst-jpg_s590x590_tt6&_nc_cat=105&ccb=1-7&_nc_sid=833d8c&_nc_ohc=JfPzw1qGw3kQ7kNvwERiG5u&_nc_oc=Adn3uRCEOdIHANfGV835CuPkjZT8kfjeuKiP5VAS7h-XKhM4R9NZyjtwUDFD2Vb0ACw&_nc_zt=23&_nc_ht=scontent-iad3-2.xx&_nc_gid=N0x--LuBn_wwHALEPHtXKw&oh=00_AfiRHqgFhDl9Ic0CgVOjtsw8dwVHLwFbvj_4-bqzb-cQtA&oe=6927C0BE",
      "width": 443,
      "height": 590,
      "id": "1021687246643648"
    },
    {
      "filename": "image_004.jpg",
      "url": "https://scontent-iad3-2.xx.fbcdn.net/v/t39.30808-6/486518239_1059009196244786_6477945239890868205_n.jpg?stp=cp6_dst-jpg_s590x590_tt6&_nc_cat=105&ccb=1-7&_nc_sid=833d8c&_nc_ohc=W0V4tILWmqQQ7kNvwEeqU37&_nc_oc=Adn8jsxBgz5aEzEYa69Ykh6-N8QIMR-WuTiNY72FxQDXV3xyAiiSDzqaxkP0GJp6uas&_nc_zt=23&_nc_ht=scontent-iad3-2.xx&_nc_gid=N0x--LuBn_wwHALEPHtXKw&oh=00_AfiJAT_4GD_CGU7hI7Jh7lQ2BsaHx7yxnMhp3Y1kg5XV3w&oe=6927C608",
      "width": 443,
      "height": 590,
      "id": "1021687173310322"
    },
    {
      "filename": "image_005.jpg",
      "url": "https://scontent-iad3-1.xx.fbcdn.net/v/t39.30808-6/485879989_1059009259578113_5851202553279318563_n.jpg?stp=cp6_dst-jpg_s590x590_tt6&_nc_cat=107&ccb=1-7&_nc_sid=833d8c&_nc_ohc=_daULuIKFiEQ7kNvwGOLK0k&_nc_oc=Adn2Utz6xKpRMrvTmnS71b2ww3omrbryU2eQdhV9YH0QumPKNqi--KciCLL8xS715a8&_nc_zt=23&_nc_ht=scontent-iad3-1.xx&_nc_gid=N0x--LuBn_wwHALEPHtXKw&oh=00_AfjKfJ8w__8qQ-B6VrB5HiGLFOoyzNok1DftNV5HT6rqVg&oe=6927D924",
      "width": 443,
      "height": 590,
      "id": "1021687326643640"
    }
  ],
  "image_count": 5,
  "extracted_at": "2025-11-22T18:11:31.415195"
}